README.rst
_description.org
lh-agpl3-LICENSE.txt
pyproject.toml
setup.py
bisos/__init__.py
bisos.transit.egg-info/PKG-INFO
bisos.transit.egg-info/SOURCES.txt
bisos.transit.egg-info/dependency_links.txt
bisos.transit.egg-info/not-zip-safe
bisos.transit.egg-info/requires.txt
bisos.transit.egg-info/top_level.txt
bisos/transit/__init__.py
bisos/transit/placeholder.py